Alab/__init__.py
Alab/get_execution_time.py
Alab-1.0.0.dist-info/LICENSE.txt
Alab-1.0.0.dist-info/METADATA
Alab-1.0.0.dist-info/WHEEL
Alab-1.0.0.dist-info/top_level.txt
Alab-1.0.0.dist-info/RECORD
