Metadata-Version: 2.1
Name: Alab
Version: 1.0.0
Summary: Jlab is a package for data analysis
Author: Adan.Y
Author-email: Adan.Y@gmail.com
Classifier: Programming Language :: Python :: 3
Classifier: License :: OSI Approved :: MIT License
Classifier: Operating System :: OS Independent
Requires-Python: >=3.5
License-File: LICENSE.txt
